{"trial_id": "b00f68088424779325a4bc3ed013da72", "hyperparameters": {"space": [{"class_name": "Int", "config": {"name": "units", "default": null, "conditions": [], "min_value": 2, "max_value": 16, "step": 2, "sampling": null}}, {"class_name": "Int", "config": {"name": "nr_layers", "default": null, "conditions": [], "min_value": 1, "max_value": 3, "step": 1, "sampling": null}}, {"class_name": "Choice", "config": {"name": "learning_rate", "default": 0.01, "conditions": [], "values": [0.01, 0.001, 0.0001], "ordered": true}}], "values": {"units": 8, "nr_layers": 1, "learning_rate": 0.01}}, "metrics": {"metrics": {"loss": {"direction": "min", "observations": [{"value": [0.5706997322081862], "step": 0}]}, "accuracy": {"direction": "max", "observations": [{"value": [0.7642339468002319], "step": 0}]}, "auc": {"direction": "min", "observations": [{"value": [0.8474361896514893], "step": 0}]}, "val_loss": {"direction": "min", "observations": [{"value": [0.5476075777514227], "step": 0}]}, "val_accuracy": {"direction": "max", "observations": [{"value": [0.7437931299209595], "step": 0}]}, "val_auc": {"direction": "max", "observations": [{"value": [0.8194653987884521], "step": 0}]}}}, "score": 0.8194653987884521, "best_step": 0, "status": "COMPLETED"}