{"trial_id": "9177dca6026f0241c21dc55620f96422", "hyperparameters": {"space": [{"class_name": "Choice", "config": {"name": "filters", "default": 4, "conditions": [], "values": [4, 8, 16, 32], "ordered": true}}, {"class_name": "Choice", "config": {"name": "cat_neurons", "default": 2, "conditions": [], "values": [2, 4, 6], "ordered": true}}, {"class_name": "Choice", "config": {"name": "hidden1_neurons", "default": 2, "conditions": [], "values": [2, 4, 6, 8, 10], "ordered": true}}, {"class_name": "Choice", "config": {"name": "pooling_", "default": "avg", "conditions": [], "values": ["avg", "max"], "ordered": false}}, {"class_name": "Choice", "config": {"name": "learning_rate", "default": 0.1, "conditions": [], "values": [0.1, 0.01, 0.001, 0.0001, 1e-05], "ordered": true}}], "values": {"filters": 8, "cat_neurons": 2, "hidden1_neurons": 10, "pooling_": "avg", "learning_rate": 1e-05}}, "metrics": {"metrics": {"loss": {"direction": "min", "observations": [{"value": [0.6913349843577834], "step": 0}]}, "accuracy": {"direction": "max", "observations": [{"value": [0.5798841118812561], "step": 0}]}, "auc": {"direction": "min", "observations": [{"value": [0.6036583781242371], "step": 0}]}, "val_loss": {"direction": "min", "observations": [{"value": [0.6886500548338194], "step": 0}]}, "val_accuracy": {"direction": "max", "observations": [{"value": [0.6971487998962402], "step": 0}]}, "val_auc": {"direction": "max", "observations": [{"value": [0.5956045985221863], "step": 0}]}}}, "score": 0.5956045985221863, "best_step": 0, "status": "COMPLETED"}