{"trial_id": "1e4f4e9c962260948d47d974b32f8e4a", "hyperparameters": {"space": [{"class_name": "Int", "config": {"name": "units", "default": null, "conditions": [], "min_value": 2, "max_value": 16, "step": 2, "sampling": null}}, {"class_name": "Int", "config": {"name": "nr_layers", "default": null, "conditions": [], "min_value": 1, "max_value": 3, "step": 1, "sampling": null}}, {"class_name": "Choice", "config": {"name": "learning_rate", "default": 0.01, "conditions": [], "values": [0.01, 0.001, 0.0001], "ordered": true}}], "values": {"units": 16, "nr_layers": 1, "learning_rate": 0.01}}, "metrics": {"metrics": {"loss": {"direction": "min", "observations": [{"value": [0.369432899602961], "step": 0}]}, "accuracy": {"direction": "max", "observations": [{"value": [0.9110226631164551], "step": 0}]}, "auc": {"direction": "min", "observations": [{"value": [0.9654375314712524], "step": 0}]}, "val_loss": {"direction": "min", "observations": [{"value": [0.33675753743830683], "step": 0}]}, "val_accuracy": {"direction": "max", "observations": [{"value": [0.9035563468933105], "step": 0}]}, "val_auc": {"direction": "max", "observations": [{"value": [0.9574280381202698], "step": 0}]}}}, "score": 0.9574280381202698, "best_step": 0, "status": "COMPLETED"}