{"ongoing_trials": {}, "hyperparameters": {"space": [{"class_name": "Choice", "config": {"name": "filters", "default": 4, "values": [4, 8, 16, 32], "ordered": true}}, {"class_name": "Choice", "config": {"name": "pooling_", "default": "avg", "values": ["avg", "max"], "ordered": false}}, {"class_name": "Choice", "config": {"name": "learning_rate", "default": 0.01, "values": [0.01, 0.001, 0.0001, 1e-05], "ordered": true}}], "values": {"filters": 4, "pooling_": "avg", "learning_rate": 0.01}}, "seed": 8394, "seed_state": 8412, "tried_so_far": ["51b79ab008e18a957a2c997e6431f949", "5190933337a724ba92d66a1149622801", "ad76dcc0ba47c69a1fea413f532bbdfc", "c13c46ced7d90fd1b3360dabe591e731", "926f50344f50e26e011ad9f107a63bfb"]}