{"trial_id": "f918ffaec17d0062c66eabe447fa8540", "hyperparameters": {"space": [{"class_name": "Int", "config": {"name": "units", "default": null, "conditions": [], "min_value": 2, "max_value": 16, "step": 2, "sampling": null}}, {"class_name": "Int", "config": {"name": "nr_layers", "default": null, "conditions": [], "min_value": 1, "max_value": 3, "step": 1, "sampling": null}}, {"class_name": "Choice", "config": {"name": "learning_rate", "default": 0.01, "conditions": [], "values": [0.01, 0.001, 0.0001], "ordered": true}}], "values": {"units": 10, "nr_layers": 3, "learning_rate": 0.001}}, "metrics": {"metrics": {"loss": {"direction": "min", "observations": [{"value": [0.432910735932613], "step": 0}]}, "accuracy": {"direction": "max", "observations": [{"value": [0.8534225225448608], "step": 0}]}, "auc": {"direction": "min", "observations": [{"value": [0.9359415769577026], "step": 0}]}, "val_loss": {"direction": "min", "observations": [{"value": [0.3842060321098785], "step": 0}]}, "val_accuracy": {"direction": "max", "observations": [{"value": [0.8483423590660095], "step": 0}]}, "val_auc": {"direction": "max", "observations": [{"value": [0.9319387674331665], "step": 0}]}}}, "score": 0.9319387674331665, "best_step": 0, "status": "COMPLETED"}