{"trial_id": "cd4d1026d88d1bcd9cfb4d27584245ea", "hyperparameters": {"space": [{"class_name": "Choice", "config": {"name": "filters", "default": 4, "conditions": [], "values": [4, 8, 16, 32], "ordered": true}}, {"class_name": "Choice", "config": {"name": "dense_1", "default": 2, "conditions": [], "values": [2, 4, 8], "ordered": true}}, {"class_name": "Choice", "config": {"name": "pooling_", "default": "avg", "conditions": [], "values": ["avg", "max"], "ordered": false}}, {"class_name": "Choice", "config": {"name": "learning_rate", "default": 0.1, "conditions": [], "values": [0.1, 0.01, 0.001, 0.0001], "ordered": true}}], "values": {"filters": 32, "dense_1": 8, "pooling_": "avg", "learning_rate": 0.01}}, "metrics": {"metrics": {"loss": {"direction": "min", "observations": [{"value": [0.647794815354002], "step": 0}]}, "accuracy": {"direction": "max", "observations": [{"value": [0.7310643792152405], "step": 0}]}, "auc": {"direction": "min", "observations": [{"value": [0.8097920417785645], "step": 0}]}, "val_loss": {"direction": "min", "observations": [{"value": [0.6877058506011963], "step": 0}]}, "val_accuracy": {"direction": "max", "observations": [{"value": [0.7232000231742859], "step": 0}]}, "val_auc": {"direction": "max", "observations": [{"value": [0.755199670791626], "step": 0}]}}}, "score": 0.755199670791626, "best_step": 0, "status": "COMPLETED"}